costa/__init__.py
costa/buildpermap.py
costa/defaults.py
costa/permap.py
costa/resources/manufacturer-data-cooling.txt
costa/resources/manufacturer-data-heating.txt
costa-0.0.1.dist-info/LICENSE
costa-0.0.1.dist-info/METADATA
costa-0.0.1.dist-info/WHEEL
costa-0.0.1.dist-info/top_level.txt
costa-0.0.1.dist-info/RECORD
