Metadata-Version: 2.1
Name: costa
Version: 0.0.1
Summary: Impute missing values in a performance table
Home-page: https://github.com/gstrugala/costa
Author: Gregor Strugala
Author-email: gregor.strugala@polymtl.ca
License: UNKNOWN
Project-URL: Bug Tracker, https://github.com/gstrugala/costa/issues
Platform: UNKNOWN
Classifier: Programming Language :: Python :: 3
Classifier: License :: OSI Approved :: MIT License
Classifier: Operating System :: OS Independent
Requires-Python: >=3.9
Requires-Dist: numpy (>=1.17.0)
Requires-Dist: pandas (>=1.1.5)
